pyfreeze/__init__.py
pyfreeze/__main__.py
pyfreeze/cli.py
pyfreeze-0.0.1.dist-info/AUTHORS.rst
pyfreeze-0.0.1.dist-info/LICENSE
pyfreeze-0.0.1.dist-info/METADATA
pyfreeze-0.0.1.dist-info/WHEEL
pyfreeze-0.0.1.dist-info/entry_points.txt
pyfreeze-0.0.1.dist-info/top_level.txt
pyfreeze-0.0.1.dist-info/RECORD
