Metadata-Version: 2.1
Name: pyfreeze
Version: 0.0.1
Summary: A small library to easily allow freezing, unfreezing and differential learning rates on weights of Pytorch models.
Home-page: https://github.com/abhitopia/pyfreeze
Author: Abhishek Aggarwal
Author-email: abhi@abhitopia.com
License: MIT license
Project-URL: Documentation, https://pyfreeze.readthedocs.io/
Project-URL: Changelog, https://pyfreeze.readthedocs.io/en/latest/changelog.html
Project-URL: Issue Tracker, https://github.com/abhitopia/pyfreeze/issues
Platform: UNKNOWN
Classifier: Development Status :: 5 - Production/Stable
Classifier: Intended Audience :: Developers
Classifier: License :: OSI Approved :: MIT License
Classifier: Operating System :: Unix
Classifier: Operating System :: POSIX
Classifier: Operating System :: Microsoft :: Windows
Classifier: Programming Language :: Python
Classifier: Programming Language :: Python :: 2.7
Classifier: Programming Language :: Python :: 3
Classifier: Programming Language :: Python :: 3.4
Classifier: Programming Language :: Python :: 3.5
Classifier: Programming Language :: Python :: 3.6
Classifier: Programming Language :: Python :: 3.7
Classifier: Programming Language :: Python :: Implementation :: CPython
Classifier: Programming Language :: Python :: Implementation :: PyPy
Classifier: Topic :: Utilities
Requires-Python: >=2.7, !=3.0.*, !=3.1.*, !=3.2.*, !=3.3.*
